{
  "metadata": {
    "fetched_at": "2026-01-27T21:01:09.396513",
    "logical_date": "2026-01-27T21:00:00+00:00",
    "dag_run_id": "scheduled__2026-01-27T21:00:00+00:00",
    "symbol": "XRPUSDT",
    "interval": "1h",
    "candles_count": 24
  },
  "data": [
    {
      "low": 1.8947,
      "high": 1.9039,
      "open": 1.8993,
      "close": 1.8996,
      "volume": 2584974.7,
      "datetime": "2026-01-26T22:00:00",
      "timestamp": 1769464800000
    },
    {
      "low": 1.8954,
      "high": 1.913,
      "open": 1.8996,
      "close": 1.9041,
      "volume": 2262878.2,
      "datetime": "2026-01-26T23:00:00",
      "timestamp": 1769468400000
    },
    {
      "low": 1.8983,
      "high": 1.905,
      "open": 1.9042,
      "close": 1.9037,
      "volume": 1604041.7,
      "datetime": "2026-01-27T00:00:00",
      "timestamp": 1769472000000
    },
    {
      "low": 1.8976,
      "high": 1.9109,
      "open": 1.9036,
      "close": 1.9063,
      "volume": 1636589.7,
      "datetime": "2026-01-27T01:00:00",
      "timestamp": 1769475600000
    },
    {
      "low": 1.905,
      "high": 1.9165,
      "open": 1.9064,
      "close": 1.9149,
      "volume": 2432000.5,
      "datetime": "2026-01-27T02:00:00",
      "timestamp": 1769479200000
    },
    {
      "low": 1.908,
      "high": 1.9169,
      "open": 1.9148,
      "close": 1.9097,
      "volume": 1970485.6,
      "datetime": "2026-01-27T03:00:00",
      "timestamp": 1769482800000
    },
    {
      "low": 1.9068,
      "high": 1.9179,
      "open": 1.9097,
      "close": 1.9089,
      "volume": 1963908.5,
      "datetime": "2026-01-27T04:00:00",
      "timestamp": 1769486400000
    },
    {
      "low": 1.9007,
      "high": 1.9093,
      "open": 1.9089,
      "close": 1.9022,
      "volume": 1434958.9,
      "datetime": "2026-01-27T05:00:00",
      "timestamp": 1769490000000
    },
    {
      "low": 1.8947,
      "high": 1.903,
      "open": 1.9022,
      "close": 1.8981,
      "volume": 1387688.7,
      "datetime": "2026-01-27T06:00:00",
      "timestamp": 1769493600000
    },
    {
      "low": 1.8971,
      "high": 1.9009,
      "open": 1.8982,
      "close": 1.8996,
      "volume": 1348402.5,
      "datetime": "2026-01-27T07:00:00",
      "timestamp": 1769497200000
    },
    {
      "low": 1.8931,
      "high": 1.9028,
      "open": 1.8995,
      "close": 1.895,
      "volume": 1220923.2,
      "datetime": "2026-01-27T08:00:00",
      "timestamp": 1769500800000
    },
    {
      "low": 1.8825,
      "high": 1.8949,
      "open": 1.8949,
      "close": 1.8833,
      "volume": 1962770.5,
      "datetime": "2026-01-27T09:00:00",
      "timestamp": 1769504400000
    },
    {
      "low": 1.8829,
      "high": 1.8895,
      "open": 1.8832,
      "close": 1.885,
      "volume": 2213387.8,
      "datetime": "2026-01-27T10:00:00",
      "timestamp": 1769508000000
    },
    {
      "low": 1.8818,
      "high": 1.8926,
      "open": 1.885,
      "close": 1.8889,
      "volume": 2542256.4,
      "datetime": "2026-01-27T11:00:00",
      "timestamp": 1769511600000
    },
    {
      "low": 1.8843,
      "high": 1.893,
      "open": 1.8889,
      "close": 1.885,
      "volume": 1663750.1,
      "datetime": "2026-01-27T12:00:00",
      "timestamp": 1769515200000
    },
    {
      "low": 1.8741,
      "high": 1.8869,
      "open": 1.885,
      "close": 1.8766,
      "volume": 2170980.9,
      "datetime": "2026-01-27T13:00:00",
      "timestamp": 1769518800000
    },
    {
      "low": 1.8757,
      "high": 1.8967,
      "open": 1.8767,
      "close": 1.8836,
      "volume": 5209015.4,
      "datetime": "2026-01-27T14:00:00",
      "timestamp": 1769522400000
    },
    {
      "low": 1.8795,
      "high": 1.8961,
      "open": 1.8837,
      "close": 1.8932,
      "volume": 2400934.6,
      "datetime": "2026-01-27T15:00:00",
      "timestamp": 1769526000000
    },
    {
      "low": 1.8926,
      "high": 1.9162,
      "open": 1.8933,
      "close": 1.9141,
      "volume": 6851809.6,
      "datetime": "2026-01-27T16:00:00",
      "timestamp": 1769529600000
    },
    {
      "low": 1.8768,
      "high": 1.9148,
      "open": 1.9141,
      "close": 1.8809,
      "volume": 5515826.5,
      "datetime": "2026-01-27T17:00:00",
      "timestamp": 1769533200000
    },
    {
      "low": 1.8785,
      "high": 1.9127,
      "open": 1.8809,
      "close": 1.9066,
      "volume": 2938371.6,
      "datetime": "2026-01-27T18:00:00",
      "timestamp": 1769536800000
    },
    {
      "low": 1.8985,
      "high": 1.9109,
      "open": 1.9067,
      "close": 1.9069,
      "volume": 2145178.7,
      "datetime": "2026-01-27T19:00:00",
      "timestamp": 1769540400000
    },
    {
      "low": 1.9058,
      "high": 1.9292,
      "open": 1.9069,
      "close": 1.9228,
      "volume": 5790038.3,
      "datetime": "2026-01-27T20:00:00",
      "timestamp": 1769544000000
    },
    {
      "low": 1.9204,
      "high": 1.9252,
      "open": 1.9228,
      "close": 1.9207,
      "volume": 101331.3,
      "datetime": "2026-01-27T21:00:00",
      "timestamp": 1769547600000
    }
  ]
}